{
  "id": "9f2c29b5-f9c0-4961-98e7-32db5b510b6a",
  "prevId": "ab9c75ba-c7be-4f44-8076-661338072f86",
  "version": "7",
  "dialect": "postgresql",
  "tables": {
    "public.audit_log": {
      "name": "audit_log",
      "schema": "",
      "columns": {
        "id": {
          "name": "id",
          "type": "uuid",
          "primaryKey": true,
          "notNull": true,
          "default": "gen_random_uuid()"
        },
        "table_name": {
          "name": "table_name",
          "type": "varchar(100)",
          "primaryKey": false,
          "notNull": true
        },
        "record_id": {
          "name": "record_id",
          "type": "uuid",
          "primaryKey": false,
          "notNull": true
        },
        "user_id": {
          "name": "user_id",
          "type": "uuid",
          "primaryKey": false,
          "notNull": false
        },
        "action": {
          "name": "action",
          "type": "varchar(50)",
          "primaryKey": false,
          "notNull": true
        },
        "old_data": {
          "name": "old_data",
          "type": "jsonb",
          "primaryKey": false,
          "notNull": false
        },
        "new_data": {
          "name": "new_data",
          "type": "jsonb",
          "primaryKey": false,
          "notNull": false
        },
        "created_at": {
          "name": "created_at",
          "type": "timestamp",
          "primaryKey": false,
          "notNull": false,
          "default": "now()"
        }
      },
      "indexes": {
        "audit_log_record_idx": {
          "name": "audit_log_record_idx",
          "columns": [
            {
              "expression": "table_name",
              "isExpression": false,
              "asc": true,
              "nulls": "last"
            },
            {
              "expression": "record_id",
              "isExpression": false,
              "asc": true,
              "nulls": "last"
            }
          ],
          "isUnique": false,
          "concurrently": false,
          "method": "btree",
          "with": {}
        }
      },
      "foreignKeys": {
        "audit_log_user_id_users_id_fk": {
          "name": "audit_log_user_id_users_id_fk",
          "tableFrom": "audit_log",
          "tableTo": "users",
          "columnsFrom": [
            "user_id"
          ],
          "columnsTo": [
            "id"
          ],
          "onDelete": "no action",
          "onUpdate": "no action"
        }
      },
      "compositePrimaryKeys": {},
      "uniqueConstraints": {},
      "policies": {},
      "checkConstraints": {},
      "isRLSEnabled": false
    },
    "public.claim_documents": {
      "name": "claim_documents",
      "schema": "",
      "columns": {
        "id": {
          "name": "id",
          "type": "uuid",
          "primaryKey": true,
          "notNull": true,
          "default": "gen_random_uuid()"
        },
        "claim_id": {
          "name": "claim_id",
          "type": "uuid",
          "primaryKey": false,
          "notNull": false
        },
        "uploaded_by": {
          "name": "uploaded_by",
          "type": "uuid",
          "primaryKey": false,
          "notNull": false
        },
        "filename": {
          "name": "filename",
          "type": "varchar(255)",
          "primaryKey": false,
          "notNull": true
        },
        "original_filename": {
          "name": "original_filename",
          "type": "varchar(255)",
          "primaryKey": false,
          "notNull": true
        },
        "file_size": {
          "name": "file_size",
          "type": "integer",
          "primaryKey": false,
          "notNull": true
        },
        "mime_type": {
          "name": "mime_type",
          "type": "varchar(100)",
          "primaryKey": false,
          "notNull": true
        },
        "file_url": {
          "name": "file_url",
          "type": "text",
          "primaryKey": false,
          "notNull": true
        },
        "document_type": {
          "name": "document_type",
          "type": "varchar(100)",
          "primaryKey": false,
          "notNull": false
        },
        "description": {
          "name": "description",
          "type": "text",
          "primaryKey": false,
          "notNull": false
        },
        "created_at": {
          "name": "created_at",
          "type": "timestamp",
          "primaryKey": false,
          "notNull": false,
          "default": "now()"
        }
      },
      "indexes": {
        "claim_documents_claim_id_idx": {
          "name": "claim_documents_claim_id_idx",
          "columns": [
            {
              "expression": "claim_id",
              "isExpression": false,
              "asc": true,
              "nulls": "last"
            }
          ],
          "isUnique": false,
          "concurrently": false,
          "method": "btree",
          "with": {}
        }
      },
      "foreignKeys": {
        "claim_documents_claim_id_claims_id_fk": {
          "name": "claim_documents_claim_id_claims_id_fk",
          "tableFrom": "claim_documents",
          "tableTo": "claims",
          "columnsFrom": [
            "claim_id"
          ],
          "columnsTo": [
            "id"
          ],
          "onDelete": "cascade",
          "onUpdate": "no action"
        },
        "claim_documents_uploaded_by_users_id_fk": {
          "name": "claim_documents_uploaded_by_users_id_fk",
          "tableFrom": "claim_documents",
          "tableTo": "users",
          "columnsFrom": [
            "uploaded_by"
          ],
          "columnsTo": [
            "id"
          ],
          "onDelete": "no action",
          "onUpdate": "no action"
        }
      },
      "compositePrimaryKeys": {},
      "uniqueConstraints": {},
      "policies": {},
      "checkConstraints": {},
      "isRLSEnabled": false
    },
    "public.claim_notes": {
      "name": "claim_notes",
      "schema": "",
      "columns": {
        "id": {
          "name": "id",
          "type": "uuid",
          "primaryKey": true,
          "notNull": true,
          "default": "gen_random_uuid()"
        },
        "claim_id": {
          "name": "claim_id",
          "type": "uuid",
          "primaryKey": false,
          "notNull": false
        },
        "user_id": {
          "name": "user_id",
          "type": "uuid",
          "primaryKey": false,
          "notNull": false
        },
        "section": {
          "name": "section",
          "type": "varchar(100)",
          "primaryKey": false,
          "notNull": true
        },
        "content": {
          "name": "content",
          "type": "text",
          "primaryKey": false,
          "notNull": true
        },
        "version": {
          "name": "version",
          "type": "integer",
          "primaryKey": false,
          "notNull": true,
          "default": 1
        },
        "is_current": {
          "name": "is_current",
          "type": "boolean",
          "primaryKey": false,
          "notNull": false,
          "default": true
        },
        "created_at": {
          "name": "created_at",
          "type": "timestamp",
          "primaryKey": false,
          "notNull": false,
          "default": "now()"
        }
      },
      "indexes": {
        "claim_notes_claim_id_idx": {
          "name": "claim_notes_claim_id_idx",
          "columns": [
            {
              "expression": "claim_id",
              "isExpression": false,
              "asc": true,
              "nulls": "last"
            }
          ],
          "isUnique": false,
          "concurrently": false,
          "method": "btree",
          "with": {}
        },
        "claim_notes_current_idx": {
          "name": "claim_notes_current_idx",
          "columns": [
            {
              "expression": "claim_id",
              "isExpression": false,
              "asc": true,
              "nulls": "last"
            },
            {
              "expression": "is_current",
              "isExpression": false,
              "asc": true,
              "nulls": "last"
            }
          ],
          "isUnique": false,
          "concurrently": false,
          "method": "btree",
          "with": {}
        }
      },
      "foreignKeys": {
        "claim_notes_claim_id_claims_id_fk": {
          "name": "claim_notes_claim_id_claims_id_fk",
          "tableFrom": "claim_notes",
          "tableTo": "claims",
          "columnsFrom": [
            "claim_id"
          ],
          "columnsTo": [
            "id"
          ],
          "onDelete": "cascade",
          "onUpdate": "no action"
        },
        "claim_notes_user_id_users_id_fk": {
          "name": "claim_notes_user_id_users_id_fk",
          "tableFrom": "claim_notes",
          "tableTo": "users",
          "columnsFrom": [
            "user_id"
          ],
          "columnsTo": [
            "id"
          ],
          "onDelete": "no action",
          "onUpdate": "no action"
        }
      },
      "compositePrimaryKeys": {},
      "uniqueConstraints": {},
      "policies": {},
      "checkConstraints": {},
      "isRLSEnabled": false
    },
    "public.claims": {
      "name": "claims",
      "schema": "",
      "columns": {
        "id": {
          "name": "id",
          "type": "uuid",
          "primaryKey": true,
          "notNull": true,
          "default": "gen_random_uuid()"
        },
        "company_id": {
          "name": "company_id",
          "type": "uuid",
          "primaryKey": false,
          "notNull": false
        },
        "created_by": {
          "name": "created_by",
          "type": "uuid",
          "primaryKey": false,
          "notNull": false
        },
        "claim_number": {
          "name": "claim_number",
          "type": "varchar(100)",
          "primaryKey": false,
          "notNull": true
        },
        "your_ref": {
          "name": "your_ref",
          "type": "varchar(100)",
          "primaryKey": false,
          "notNull": false
        },
        "our_ref": {
          "name": "our_ref",
          "type": "varchar(100)",
          "primaryKey": false,
          "notNull": false
        },
        "invoice_number": {
          "name": "invoice_number",
          "type": "varchar(100)",
          "primaryKey": false,
          "notNull": false
        },
        "date_received": {
          "name": "date_received",
          "type": "timestamp",
          "primaryKey": false,
          "notNull": false
        },
        "date_inspected": {
          "name": "date_inspected",
          "type": "timestamp",
          "primaryKey": false,
          "notNull": false
        },
        "date_of_loss": {
          "name": "date_of_loss",
          "type": "timestamp",
          "primaryKey": false,
          "notNull": false
        },
        "letter_date": {
          "name": "letter_date",
          "type": "timestamp",
          "primaryKey": false,
          "notNull": false
        },
        "insured_name": {
          "name": "insured_name",
          "type": "varchar(255)",
          "primaryKey": false,
          "notNull": false
        },
        "insured_address": {
          "name": "insured_address",
          "type": "text",
          "primaryKey": false,
          "notNull": false
        },
        "third_party_name": {
          "name": "third_party_name",
          "type": "varchar(255)",
          "primaryKey": false,
          "notNull": false
        },
        "third_party_vehicle": {
          "name": "third_party_vehicle",
          "type": "varchar(255)",
          "primaryKey": false,
          "notNull": false
        },
        "vehicle_data": {
          "name": "vehicle_data",
          "type": "jsonb",
          "primaryKey": false,
          "notNull": true,
          "default": "'{}'::jsonb"
        },
        "damage_data": {
          "name": "damage_data",
          "type": "jsonb",
          "primaryKey": false,
          "notNull": false,
          "default": "'{}'::jsonb"
        },
        "estimate_data": {
          "name": "estimate_data",
          "type": "jsonb",
          "primaryKey": false,
          "notNull": false,
          "default": "'{}'::jsonb"
        },
        "recommendation_data": {
          "name": "recommendation_data",
          "type": "jsonb",
          "primaryKey": false,
          "notNull": false,
          "default": "'{}'::jsonb"
        },
        "place_of_inspection": {
          "name": "place_of_inspection",
          "type": "varchar(255)",
          "primaryKey": false,
          "notNull": false
        },
        "claims_technician": {
          "name": "claims_technician",
          "type": "varchar(255)",
          "primaryKey": false,
          "notNull": false
        },
        "witness": {
          "name": "witness",
          "type": "varchar(255)",
          "primaryKey": false,
          "notNull": false
        },
        "number_of_photographs": {
          "name": "number_of_photographs",
          "type": "integer",
          "primaryKey": false,
          "notNull": false,
          "default": 0
        },
        "cancellation_reason": {
          "name": "cancellation_reason",
          "type": "text",
          "primaryKey": false,
          "notNull": false
        },
        "status": {
          "name": "status",
          "type": "varchar(50)",
          "primaryKey": false,
          "notNull": false,
          "default": "'pending'"
        },
        "current_step": {
          "name": "current_step",
          "type": "varchar(50)",
          "primaryKey": false,
          "notNull": false,
          "default": "'documents'"
        },
        "created_at": {
          "name": "created_at",
          "type": "timestamp",
          "primaryKey": false,
          "notNull": false,
          "default": "now()"
        },
        "updated_at": {
          "name": "updated_at",
          "type": "timestamp",
          "primaryKey": false,
          "notNull": false,
          "default": "now()"
        },
        "completed_at": {
          "name": "completed_at",
          "type": "timestamp",
          "primaryKey": false,
          "notNull": false
        }
      },
      "indexes": {
        "claims_company_id_idx": {
          "name": "claims_company_id_idx",
          "columns": [
            {
              "expression": "company_id",
              "isExpression": false,
              "asc": true,
              "nulls": "last"
            }
          ],
          "isUnique": false,
          "concurrently": false,
          "method": "btree",
          "with": {}
        },
        "claims_status_idx": {
          "name": "claims_status_idx",
          "columns": [
            {
              "expression": "status",
              "isExpression": false,
              "asc": true,
              "nulls": "last"
            }
          ],
          "isUnique": false,
          "concurrently": false,
          "method": "btree",
          "with": {}
        },
        "claims_created_at_idx": {
          "name": "claims_created_at_idx",
          "columns": [
            {
              "expression": "created_at",
              "isExpression": false,
              "asc": true,
              "nulls": "last"
            }
          ],
          "isUnique": false,
          "concurrently": false,
          "method": "btree",
          "with": {}
        },
        "claims_claim_number_idx": {
          "name": "claims_claim_number_idx",
          "columns": [
            {
              "expression": "claim_number",
              "isExpression": false,
              "asc": true,
              "nulls": "last"
            }
          ],
          "isUnique": true,
          "concurrently": false,
          "method": "btree",
          "with": {}
        }
      },
      "foreignKeys": {
        "claims_company_id_companies_id_fk": {
          "name": "claims_company_id_companies_id_fk",
          "tableFrom": "claims",
          "tableTo": "companies",
          "columnsFrom": [
            "company_id"
          ],
          "columnsTo": [
            "id"
          ],
          "onDelete": "cascade",
          "onUpdate": "no action"
        },
        "claims_created_by_users_id_fk": {
          "name": "claims_created_by_users_id_fk",
          "tableFrom": "claims",
          "tableTo": "users",
          "columnsFrom": [
            "created_by"
          ],
          "columnsTo": [
            "id"
          ],
          "onDelete": "no action",
          "onUpdate": "no action"
        }
      },
      "compositePrimaryKeys": {},
      "uniqueConstraints": {
        "claims_claim_number_unique": {
          "name": "claims_claim_number_unique",
          "nullsNotDistinct": false,
          "columns": [
            "claim_number"
          ]
        }
      },
      "policies": {},
      "checkConstraints": {},
      "isRLSEnabled": false
    },
    "public.companies": {
      "name": "companies",
      "schema": "",
      "columns": {
        "id": {
          "name": "id",
          "type": "uuid",
          "primaryKey": true,
          "notNull": true,
          "default": "gen_random_uuid()"
        },
        "name": {
          "name": "name",
          "type": "varchar(255)",
          "primaryKey": false,
          "notNull": true
        },
        "first_name": {
          "name": "first_name",
          "type": "varchar(100)",
          "primaryKey": false,
          "notNull": true
        },
        "last_name": {
          "name": "last_name",
          "type": "varchar(100)",
          "primaryKey": false,
          "notNull": true
        },
        "address": {
          "name": "address",
          "type": "text",
          "primaryKey": false,
          "notNull": false
        },
        "phone": {
          "name": "phone",
          "type": "varchar(50)",
          "primaryKey": false,
          "notNull": true
        },
        "email": {
          "name": "email",
          "type": "varchar(255)",
          "primaryKey": false,
          "notNull": true
        },
        "plan": {
          "name": "plan",
          "type": "varchar(100)",
          "primaryKey": false,
          "notNull": false
        },
        "settings": {
          "name": "settings",
          "type": "jsonb",
          "primaryKey": false,
          "notNull": false,
          "default": "'{}'::jsonb"
        },
        "created_at": {
          "name": "created_at",
          "type": "timestamp",
          "primaryKey": false,
          "notNull": false,
          "default": "now()"
        },
        "updated_at": {
          "name": "updated_at",
          "type": "timestamp",
          "primaryKey": false,
          "notNull": false,
          "default": "now()"
        }
      },
      "indexes": {},
      "foreignKeys": {},
      "compositePrimaryKeys": {},
      "uniqueConstraints": {},
      "policies": {},
      "checkConstraints": {},
      "isRLSEnabled": false
    },
    "public.company_pins": {
      "name": "company_pins",
      "schema": "",
      "columns": {
        "id": {
          "name": "id",
          "type": "uuid",
          "primaryKey": true,
          "notNull": true,
          "default": "gen_random_uuid()"
        },
        "company_id": {
          "name": "company_id",
          "type": "uuid",
          "primaryKey": false,
          "notNull": false
        },
        "created_by": {
          "name": "created_by",
          "type": "varchar(255)",
          "primaryKey": false,
          "notNull": true
        },
        "first_name": {
          "name": "first_name",
          "type": "varchar(100)",
          "primaryKey": false,
          "notNull": true
        },
        "last_name": {
          "name": "last_name",
          "type": "varchar(100)",
          "primaryKey": false,
          "notNull": true
        },
        "user_role": {
          "name": "user_role",
          "type": "varchar(50)",
          "primaryKey": false,
          "notNull": true
        },
        "pin": {
          "name": "pin",
          "type": "varchar(10)",
          "primaryKey": false,
          "notNull": true
        },
        "uses_remaining": {
          "name": "uses_remaining",
          "type": "integer",
          "primaryKey": false,
          "notNull": false,
          "default": 3
        },
        "max_uses": {
          "name": "max_uses",
          "type": "integer",
          "primaryKey": false,
          "notNull": false,
          "default": 3
        },
        "created_at": {
          "name": "created_at",
          "type": "timestamp",
          "primaryKey": false,
          "notNull": false,
          "default": "now()"
        },
        "expires_at": {
          "name": "expires_at",
          "type": "timestamp",
          "primaryKey": false,
          "notNull": true
        },
        "locked_until": {
          "name": "locked_until",
          "type": "timestamp",
          "primaryKey": false,
          "notNull": false
        },
        "failed_attempts": {
          "name": "failed_attempts",
          "type": "integer",
          "primaryKey": false,
          "notNull": false,
          "default": 0
        }
      },
      "indexes": {
        "company_pins_company_id_idx": {
          "name": "company_pins_company_id_idx",
          "columns": [
            {
              "expression": "company_id",
              "isExpression": false,
              "asc": true,
              "nulls": "last"
            }
          ],
          "isUnique": false,
          "concurrently": false,
          "method": "btree",
          "with": {}
        },
        "company_pins_expires_at_idx": {
          "name": "company_pins_expires_at_idx",
          "columns": [
            {
              "expression": "expires_at",
              "isExpression": false,
              "asc": true,
              "nulls": "last"
            }
          ],
          "isUnique": false,
          "concurrently": false,
          "method": "btree",
          "with": {}
        },
        "company_pins_created_by_idx": {
          "name": "company_pins_created_by_idx",
          "columns": [
            {
              "expression": "created_by",
              "isExpression": false,
              "asc": true,
              "nulls": "last"
            }
          ],
          "isUnique": false,
          "concurrently": false,
          "method": "btree",
          "with": {}
        },
        "company_pins_unique_active": {
          "name": "company_pins_unique_active",
          "columns": [
            {
              "expression": "company_id",
              "isExpression": false,
              "asc": true,
              "nulls": "last"
            },
            {
              "expression": "first_name",
              "isExpression": false,
              "asc": true,
              "nulls": "last"
            },
            {
              "expression": "last_name",
              "isExpression": false,
              "asc": true,
              "nulls": "last"
            }
          ],
          "isUnique": true,
          "concurrently": false,
          "method": "btree",
          "with": {}
        },
        "company_pins_lookup_idx": {
          "name": "company_pins_lookup_idx",
          "columns": [
            {
              "expression": "company_id",
              "isExpression": false,
              "asc": true,
              "nulls": "last"
            },
            {
              "expression": "first_name",
              "isExpression": false,
              "asc": true,
              "nulls": "last"
            },
            {
              "expression": "last_name",
              "isExpression": false,
              "asc": true,
              "nulls": "last"
            },
            {
              "expression": "pin",
              "isExpression": false,
              "asc": true,
              "nulls": "last"
            }
          ],
          "isUnique": false,
          "concurrently": false,
          "method": "btree",
          "with": {}
        }
      },
      "foreignKeys": {
        "company_pins_company_id_companies_id_fk": {
          "name": "company_pins_company_id_companies_id_fk",
          "tableFrom": "company_pins",
          "tableTo": "companies",
          "columnsFrom": [
            "company_id"
          ],
          "columnsTo": [
            "id"
          ],
          "onDelete": "cascade",
          "onUpdate": "no action"
        }
      },
      "compositePrimaryKeys": {},
      "uniqueConstraints": {},
      "policies": {},
      "checkConstraints": {},
      "isRLSEnabled": false
    },
    "public.invoices": {
      "name": "invoices",
      "schema": "",
      "columns": {
        "id": {
          "name": "id",
          "type": "uuid",
          "primaryKey": true,
          "notNull": true,
          "default": "gen_random_uuid()"
        },
        "company_id": {
          "name": "company_id",
          "type": "uuid",
          "primaryKey": false,
          "notNull": false
        },
        "claim_id": {
          "name": "claim_id",
          "type": "uuid",
          "primaryKey": false,
          "notNull": false
        },
        "invoice_number": {
          "name": "invoice_number",
          "type": "varchar(100)",
          "primaryKey": false,
          "notNull": true
        },
        "invoice_date": {
          "name": "invoice_date",
          "type": "timestamp",
          "primaryKey": false,
          "notNull": true
        },
        "due_date": {
          "name": "due_date",
          "type": "timestamp",
          "primaryKey": false,
          "notNull": false
        },
        "bill_to_name": {
          "name": "bill_to_name",
          "type": "varchar(255)",
          "primaryKey": false,
          "notNull": true
        },
        "bill_to_address": {
          "name": "bill_to_address",
          "type": "text",
          "primaryKey": false,
          "notNull": true
        },
        "subtotal": {
          "name": "subtotal",
          "type": "numeric(10, 2)",
          "primaryKey": false,
          "notNull": true
        },
        "vat_rate": {
          "name": "vat_rate",
          "type": "numeric(5, 2)",
          "primaryKey": false,
          "notNull": false,
          "default": "'12.5'"
        },
        "vat_amount": {
          "name": "vat_amount",
          "type": "numeric(10, 2)",
          "primaryKey": false,
          "notNull": true
        },
        "total_amount": {
          "name": "total_amount",
          "type": "numeric(10, 2)",
          "primaryKey": false,
          "notNull": true
        },
        "line_items": {
          "name": "line_items",
          "type": "jsonb",
          "primaryKey": false,
          "notNull": true,
          "default": "'[]'::jsonb"
        },
        "status": {
          "name": "status",
          "type": "varchar(50)",
          "primaryKey": false,
          "notNull": false,
          "default": "'draft'"
        },
        "created_at": {
          "name": "created_at",
          "type": "timestamp",
          "primaryKey": false,
          "notNull": false,
          "default": "now()"
        },
        "updated_at": {
          "name": "updated_at",
          "type": "timestamp",
          "primaryKey": false,
          "notNull": false,
          "default": "now()"
        }
      },
      "indexes": {
        "invoices_company_id_idx": {
          "name": "invoices_company_id_idx",
          "columns": [
            {
              "expression": "company_id",
              "isExpression": false,
              "asc": true,
              "nulls": "last"
            }
          ],
          "isUnique": false,
          "concurrently": false,
          "method": "btree",
          "with": {}
        },
        "invoices_invoice_number_idx": {
          "name": "invoices_invoice_number_idx",
          "columns": [
            {
              "expression": "invoice_number",
              "isExpression": false,
              "asc": true,
              "nulls": "last"
            }
          ],
          "isUnique": true,
          "concurrently": false,
          "method": "btree",
          "with": {}
        }
      },
      "foreignKeys": {
        "invoices_company_id_companies_id_fk": {
          "name": "invoices_company_id_companies_id_fk",
          "tableFrom": "invoices",
          "tableTo": "companies",
          "columnsFrom": [
            "company_id"
          ],
          "columnsTo": [
            "id"
          ],
          "onDelete": "cascade",
          "onUpdate": "no action"
        },
        "invoices_claim_id_claims_id_fk": {
          "name": "invoices_claim_id_claims_id_fk",
          "tableFrom": "invoices",
          "tableTo": "claims",
          "columnsFrom": [
            "claim_id"
          ],
          "columnsTo": [
            "id"
          ],
          "onDelete": "no action",
          "onUpdate": "no action"
        }
      },
      "compositePrimaryKeys": {},
      "uniqueConstraints": {
        "invoices_invoice_number_unique": {
          "name": "invoices_invoice_number_unique",
          "nullsNotDistinct": false,
          "columns": [
            "invoice_number"
          ]
        }
      },
      "policies": {},
      "checkConstraints": {},
      "isRLSEnabled": false
    },
    "public.reports": {
      "name": "reports",
      "schema": "",
      "columns": {
        "id": {
          "name": "id",
          "type": "uuid",
          "primaryKey": true,
          "notNull": true,
          "default": "gen_random_uuid()"
        },
        "claim_id": {
          "name": "claim_id",
          "type": "uuid",
          "primaryKey": false,
          "notNull": false
        },
        "company_id": {
          "name": "company_id",
          "type": "uuid",
          "primaryKey": false,
          "notNull": false
        },
        "generated_by": {
          "name": "generated_by",
          "type": "uuid",
          "primaryKey": false,
          "notNull": false
        },
        "report_type": {
          "name": "report_type",
          "type": "varchar(50)",
          "primaryKey": false,
          "notNull": false,
          "default": "'assessment'"
        },
        "report_number": {
          "name": "report_number",
          "type": "varchar(100)",
          "primaryKey": false,
          "notNull": true
        },
        "report_data": {
          "name": "report_data",
          "type": "jsonb",
          "primaryKey": false,
          "notNull": true
        },
        "pdf_url": {
          "name": "pdf_url",
          "type": "text",
          "primaryKey": false,
          "notNull": false
        },
        "pdf_filename": {
          "name": "pdf_filename",
          "type": "varchar(255)",
          "primaryKey": false,
          "notNull": false
        },
        "status": {
          "name": "status",
          "type": "varchar(50)",
          "primaryKey": false,
          "notNull": false,
          "default": "'generated'"
        },
        "created_at": {
          "name": "created_at",
          "type": "timestamp",
          "primaryKey": false,
          "notNull": false,
          "default": "now()"
        }
      },
      "indexes": {
        "reports_company_id_idx": {
          "name": "reports_company_id_idx",
          "columns": [
            {
              "expression": "company_id",
              "isExpression": false,
              "asc": true,
              "nulls": "last"
            }
          ],
          "isUnique": false,
          "concurrently": false,
          "method": "btree",
          "with": {}
        },
        "reports_claim_id_idx": {
          "name": "reports_claim_id_idx",
          "columns": [
            {
              "expression": "claim_id",
              "isExpression": false,
              "asc": true,
              "nulls": "last"
            }
          ],
          "isUnique": false,
          "concurrently": false,
          "method": "btree",
          "with": {}
        },
        "reports_report_number_idx": {
          "name": "reports_report_number_idx",
          "columns": [
            {
              "expression": "report_number",
              "isExpression": false,
              "asc": true,
              "nulls": "last"
            }
          ],
          "isUnique": true,
          "concurrently": false,
          "method": "btree",
          "with": {}
        }
      },
      "foreignKeys": {
        "reports_claim_id_claims_id_fk": {
          "name": "reports_claim_id_claims_id_fk",
          "tableFrom": "reports",
          "tableTo": "claims",
          "columnsFrom": [
            "claim_id"
          ],
          "columnsTo": [
            "id"
          ],
          "onDelete": "cascade",
          "onUpdate": "no action"
        },
        "reports_company_id_companies_id_fk": {
          "name": "reports_company_id_companies_id_fk",
          "tableFrom": "reports",
          "tableTo": "companies",
          "columnsFrom": [
            "company_id"
          ],
          "columnsTo": [
            "id"
          ],
          "onDelete": "cascade",
          "onUpdate": "no action"
        },
        "reports_generated_by_users_id_fk": {
          "name": "reports_generated_by_users_id_fk",
          "tableFrom": "reports",
          "tableTo": "users",
          "columnsFrom": [
            "generated_by"
          ],
          "columnsTo": [
            "id"
          ],
          "onDelete": "no action",
          "onUpdate": "no action"
        }
      },
      "compositePrimaryKeys": {},
      "uniqueConstraints": {
        "reports_report_number_unique": {
          "name": "reports_report_number_unique",
          "nullsNotDistinct": false,
          "columns": [
            "report_number"
          ]
        }
      },
      "policies": {},
      "checkConstraints": {},
      "isRLSEnabled": false
    },
    "public.users": {
      "name": "users",
      "schema": "",
      "columns": {
        "id": {
          "name": "id",
          "type": "uuid",
          "primaryKey": true,
          "notNull": true,
          "default": "gen_random_uuid()"
        },
        "clerk_id": {
          "name": "clerk_id",
          "type": "varchar(255)",
          "primaryKey": false,
          "notNull": false
        },
        "company_id": {
          "name": "company_id",
          "type": "uuid",
          "primaryKey": false,
          "notNull": false
        },
        "email": {
          "name": "email",
          "type": "varchar(255)",
          "primaryKey": false,
          "notNull": true
        },
        "first_name": {
          "name": "first_name",
          "type": "varchar(100)",
          "primaryKey": false,
          "notNull": true
        },
        "last_name": {
          "name": "last_name",
          "type": "varchar(100)",
          "primaryKey": false,
          "notNull": true
        },
        "role": {
          "name": "role",
          "type": "varchar(50)",
          "primaryKey": false,
          "notNull": true
        },
        "pin": {
          "name": "pin",
          "type": "varchar(10)",
          "primaryKey": false,
          "notNull": false
        },
        "pin_created_at": {
          "name": "pin_created_at",
          "type": "timestamp",
          "primaryKey": false,
          "notNull": false
        },
        "pin_uses_remaining": {
          "name": "pin_uses_remaining",
          "type": "integer",
          "primaryKey": false,
          "notNull": false,
          "default": 3
        },
        "pin_expires_at": {
          "name": "pin_expires_at",
          "type": "timestamp",
          "primaryKey": false,
          "notNull": false
        },
        "pin_locked_until": {
          "name": "pin_locked_until",
          "type": "timestamp",
          "primaryKey": false,
          "notNull": false
        },
        "is_active": {
          "name": "is_active",
          "type": "boolean",
          "primaryKey": false,
          "notNull": false,
          "default": true
        },
        "last_login": {
          "name": "last_login",
          "type": "timestamp",
          "primaryKey": false,
          "notNull": false
        },
        "created_at": {
          "name": "created_at",
          "type": "timestamp",
          "primaryKey": false,
          "notNull": false,
          "default": "now()"
        },
        "updated_at": {
          "name": "updated_at",
          "type": "timestamp",
          "primaryKey": false,
          "notNull": false,
          "default": "now()"
        }
      },
      "indexes": {
        "users_clerk_id_idx": {
          "name": "users_clerk_id_idx",
          "columns": [
            {
              "expression": "clerk_id",
              "isExpression": false,
              "asc": true,
              "nulls": "last"
            }
          ],
          "isUnique": true,
          "concurrently": false,
          "method": "btree",
          "with": {}
        },
        "users_company_id_idx": {
          "name": "users_company_id_idx",
          "columns": [
            {
              "expression": "company_id",
              "isExpression": false,
              "asc": true,
              "nulls": "last"
            }
          ],
          "isUnique": false,
          "concurrently": false,
          "method": "btree",
          "with": {}
        },
        "users_pin_expires_idx": {
          "name": "users_pin_expires_idx",
          "columns": [
            {
              "expression": "pin_expires_at",
              "isExpression": false,
              "asc": true,
              "nulls": "last"
            }
          ],
          "isUnique": false,
          "concurrently": false,
          "method": "btree",
          "with": {}
        }
      },
      "foreignKeys": {
        "users_company_id_companies_id_fk": {
          "name": "users_company_id_companies_id_fk",
          "tableFrom": "users",
          "tableTo": "companies",
          "columnsFrom": [
            "company_id"
          ],
          "columnsTo": [
            "id"
          ],
          "onDelete": "cascade",
          "onUpdate": "no action"
        }
      },
      "compositePrimaryKeys": {},
      "uniqueConstraints": {
        "users_clerk_id_unique": {
          "name": "users_clerk_id_unique",
          "nullsNotDistinct": false,
          "columns": [
            "clerk_id"
          ]
        }
      },
      "policies": {},
      "checkConstraints": {},
      "isRLSEnabled": false
    }
  },
  "enums": {},
  "schemas": {},
  "sequences": {},
  "roles": {},
  "policies": {},
  "views": {},
  "_meta": {
    "columns": {},
    "schemas": {},
    "tables": {}
  }
}