{
  "id": "8f54a2ab-5bcf-4005-b6c0-86e1366c0640",
  "prevId": "9f2c29b5-f9c0-4961-98e7-32db5b510b6a",
  "version": "7",
  "dialect": "postgresql",
  "tables": {
    "public.claims": {
      "name": "claims",
      "schema": "",
      "columns": {
        "id": {
          "name": "id",
          "type": "uuid",
          "primaryKey": true,
          "notNull": true,
          "default": "gen_random_uuid()"
        },
        "company_id": {
          "name": "company_id",
          "type": "uuid",
          "primaryKey": false,
          "notNull": false
        },
        "created_by": {
          "name": "created_by",
          "type": "varchar(255)",
          "primaryKey": false,
          "notNull": false
        },
        "claim_number": {
          "name": "claim_number",
          "type": "varchar(100)",
          "primaryKey": false,
          "notNull": true
        },
        "your_ref": {
          "name": "your_ref",
          "type": "varchar(100)",
          "primaryKey": false,
          "notNull": false
        },
        "our_ref": {
          "name": "our_ref",
          "type": "varchar(100)",
          "primaryKey": false,
          "notNull": false
        },
        "invoice_number": {
          "name": "invoice_number",
          "type": "varchar(100)",
          "primaryKey": false,
          "notNull": false
        },
        "date_received": {
          "name": "date_received",
          "type": "timestamp",
          "primaryKey": false,
          "notNull": false
        },
        "date_inspected": {
          "name": "date_inspected",
          "type": "timestamp",
          "primaryKey": false,
          "notNull": false
        },
        "date_of_loss": {
          "name": "date_of_loss",
          "type": "timestamp",
          "primaryKey": false,
          "notNull": false
        },
        "letter_date": {
          "name": "letter_date",
          "type": "timestamp",
          "primaryKey": false,
          "notNull": false
        },
        "insured_name": {
          "name": "insured_name",
          "type": "varchar(255)",
          "primaryKey": false,
          "notNull": false
        },
        "insured_address": {
          "name": "insured_address",
          "type": "text",
          "primaryKey": false,
          "notNull": false
        },
        "third_party_name": {
          "name": "third_party_name",
          "type": "varchar(255)",
          "primaryKey": false,
          "notNull": false
        },
        "third_party_vehicle": {
          "name": "third_party_vehicle",
          "type": "varchar(255)",
          "primaryKey": false,
          "notNull": false
        },
        "vehicle_data": {
          "name": "vehicle_data",
          "type": "jsonb",
          "primaryKey": false,
          "notNull": true,
          "default": "'{}'::jsonb"
        },
        "damage_data": {
          "name": "damage_data",
          "type": "jsonb",
          "primaryKey": false,
          "notNull": false,
          "default": "'{}'::jsonb"
        },
        "estimate_data": {
          "name": "estimate_data",
          "type": "jsonb",
          "primaryKey": false,
          "notNull": false,
          "default": "'{}'::jsonb"
        },
        "recommendation_data": {
          "name": "recommendation_data",
          "type": "jsonb",
          "primaryKey": false,
          "notNull": false,
          "default": "'{}'::jsonb"
        },
        "place_of_inspection": {
          "name": "place_of_inspection",
          "type": "varchar(255)",
          "primaryKey": false,
          "notNull": false
        },
        "claims_technician": {
          "name": "claims_technician",
          "type": "varchar(255)",
          "primaryKey": false,
          "notNull": false
        },
        "witness": {
          "name": "witness",
          "type": "varchar(255)",
          "primaryKey": false,
          "notNull": false
        },
        "number_of_photographs": {
          "name": "number_of_photographs",
          "type": "integer",
          "primaryKey": false,
          "notNull": false,
          "default": 0
        },
        "cancellation_reason": {
          "name": "cancellation_reason",
          "type": "text",
          "primaryKey": false,
          "notNull": false
        },
        "status": {
          "name": "status",
          "type": "varchar(50)",
          "primaryKey": false,
          "notNull": false,
          "default": "'pending'"
        },
        "current_step": {
          "name": "current_step",
          "type": "varchar(50)",
          "primaryKey": false,
          "notNull": false,
          "default": "'documents'"
        },
        "created_at": {
          "name": "created_at",
          "type": "timestamp",
          "primaryKey": false,
          "notNull": false,
          "default": "now()"
        },
        "updated_at": {
          "name": "updated_at",
          "type": "timestamp",
          "primaryKey": false,
          "notNull": false,
          "default": "now()"
        },
        "completed_at": {
          "name": "completed_at",
          "type": "timestamp",
          "primaryKey": false,
          "notNull": false
        }
      },
      "indexes": {
        "claims_company_id_idx": {
          "name": "claims_company_id_idx",
          "columns": [
            {
              "expression": "company_id",
              "isExpression": false,
              "asc": true,
              "nulls": "last"
            }
          ],
          "isUnique": false,
          "concurrently": false,
          "method": "btree",
          "with": {}
        },
        "claims_status_idx": {
          "name": "claims_status_idx",
          "columns": [
            {
              "expression": "status",
              "isExpression": false,
              "asc": true,
              "nulls": "last"
            }
          ],
          "isUnique": false,
          "concurrently": false,
          "method": "btree",
          "with": {}
        },
        "claims_created_at_idx": {
          "name": "claims_created_at_idx",
          "columns": [
            {
              "expression": "created_at",
              "isExpression": false,
              "asc": true,
              "nulls": "last"
            }
          ],
          "isUnique": false,
          "concurrently": false,
          "method": "btree",
          "with": {}
        },
        "claims_claim_number_idx": {
          "name": "claims_claim_number_idx",
          "columns": [
            {
              "expression": "claim_number",
              "isExpression": false,
              "asc": true,
              "nulls": "last"
            }
          ],
          "isUnique": true,
          "concurrently": false,
          "method": "btree",
          "with": {}
        }
      },
      "foreignKeys": {
        "claims_company_id_companies_id_fk": {
          "name": "claims_company_id_companies_id_fk",
          "tableFrom": "claims",
          "tableTo": "companies",
          "columnsFrom": [
            "company_id"
          ],
          "columnsTo": [
            "id"
          ],
          "onDelete": "cascade",
          "onUpdate": "no action"
        }
      },
      "compositePrimaryKeys": {},
      "uniqueConstraints": {
        "claims_claim_number_unique": {
          "name": "claims_claim_number_unique",
          "nullsNotDistinct": false,
          "columns": [
            "claim_number"
          ]
        }
      },
      "policies": {},
      "checkConstraints": {},
      "isRLSEnabled": false
    },
    "public.companies": {
      "name": "companies",
      "schema": "",
      "columns": {
        "id": {
          "name": "id",
          "type": "uuid",
          "primaryKey": true,
          "notNull": true,
          "default": "gen_random_uuid()"
        },
        "name": {
          "name": "name",
          "type": "varchar(255)",
          "primaryKey": false,
          "notNull": true
        },
        "first_name": {
          "name": "first_name",
          "type": "varchar(100)",
          "primaryKey": false,
          "notNull": true
        },
        "last_name": {
          "name": "last_name",
          "type": "varchar(100)",
          "primaryKey": false,
          "notNull": true
        },
        "address": {
          "name": "address",
          "type": "text",
          "primaryKey": false,
          "notNull": false
        },
        "email": {
          "name": "email",
          "type": "varchar(255)",
          "primaryKey": false,
          "notNull": true
        },
        "phone": {
          "name": "phone",
          "type": "varchar(50)",
          "primaryKey": false,
          "notNull": true
        },
        "plan": {
          "name": "plan",
          "type": "varchar(100)",
          "primaryKey": false,
          "notNull": false
        },
        "settings": {
          "name": "settings",
          "type": "jsonb",
          "primaryKey": false,
          "notNull": false,
          "default": "'{}'::jsonb"
        },
        "created_at": {
          "name": "created_at",
          "type": "timestamp",
          "primaryKey": false,
          "notNull": false,
          "default": "now()"
        },
        "updated_at": {
          "name": "updated_at",
          "type": "timestamp",
          "primaryKey": false,
          "notNull": false,
          "default": "now()"
        }
      },
      "indexes": {},
      "foreignKeys": {},
      "compositePrimaryKeys": {},
      "uniqueConstraints": {},
      "policies": {},
      "checkConstraints": {},
      "isRLSEnabled": false
    },
    "public.reports": {
      "name": "reports",
      "schema": "",
      "columns": {
        "id": {
          "name": "id",
          "type": "uuid",
          "primaryKey": true,
          "notNull": true,
          "default": "gen_random_uuid()"
        },
        "claim_id": {
          "name": "claim_id",
          "type": "uuid",
          "primaryKey": false,
          "notNull": false
        },
        "company_id": {
          "name": "company_id",
          "type": "uuid",
          "primaryKey": false,
          "notNull": false
        },
        "generated_by": {
          "name": "generated_by",
          "type": "varchar(255)",
          "primaryKey": false,
          "notNull": false
        },
        "report_type": {
          "name": "report_type",
          "type": "varchar(50)",
          "primaryKey": false,
          "notNull": false,
          "default": "'assessment'"
        },
        "report_number": {
          "name": "report_number",
          "type": "varchar(100)",
          "primaryKey": false,
          "notNull": true
        },
        "report_data": {
          "name": "report_data",
          "type": "jsonb",
          "primaryKey": false,
          "notNull": true
        },
        "pdf_url": {
          "name": "pdf_url",
          "type": "text",
          "primaryKey": false,
          "notNull": false
        },
        "pdf_filename": {
          "name": "pdf_filename",
          "type": "varchar(255)",
          "primaryKey": false,
          "notNull": false
        },
        "pdf_data": {
          "name": "pdf_data",
          "type": "text",
          "primaryKey": false,
          "notNull": false
        },
        "status": {
          "name": "status",
          "type": "varchar(50)",
          "primaryKey": false,
          "notNull": false,
          "default": "'generated'"
        },
        "created_at": {
          "name": "created_at",
          "type": "timestamp",
          "primaryKey": false,
          "notNull": false,
          "default": "now()"
        }
      },
      "indexes": {
        "reports_company_id_idx": {
          "name": "reports_company_id_idx",
          "columns": [
            {
              "expression": "company_id",
              "isExpression": false,
              "asc": true,
              "nulls": "last"
            }
          ],
          "isUnique": false,
          "concurrently": false,
          "method": "btree",
          "with": {}
        },
        "reports_claim_id_idx": {
          "name": "reports_claim_id_idx",
          "columns": [
            {
              "expression": "claim_id",
              "isExpression": false,
              "asc": true,
              "nulls": "last"
            }
          ],
          "isUnique": false,
          "concurrently": false,
          "method": "btree",
          "with": {}
        },
        "reports_report_number_idx": {
          "name": "reports_report_number_idx",
          "columns": [
            {
              "expression": "report_number",
              "isExpression": false,
              "asc": true,
              "nulls": "last"
            }
          ],
          "isUnique": true,
          "concurrently": false,
          "method": "btree",
          "with": {}
        }
      },
      "foreignKeys": {
        "reports_claim_id_claims_id_fk": {
          "name": "reports_claim_id_claims_id_fk",
          "tableFrom": "reports",
          "tableTo": "claims",
          "columnsFrom": [
            "claim_id"
          ],
          "columnsTo": [
            "id"
          ],
          "onDelete": "cascade",
          "onUpdate": "no action"
        },
        "reports_company_id_companies_id_fk": {
          "name": "reports_company_id_companies_id_fk",
          "tableFrom": "reports",
          "tableTo": "companies",
          "columnsFrom": [
            "company_id"
          ],
          "columnsTo": [
            "id"
          ],
          "onDelete": "cascade",
          "onUpdate": "no action"
        }
      },
      "compositePrimaryKeys": {},
      "uniqueConstraints": {
        "reports_report_number_unique": {
          "name": "reports_report_number_unique",
          "nullsNotDistinct": false,
          "columns": [
            "report_number"
          ]
        }
      },
      "policies": {},
      "checkConstraints": {},
      "isRLSEnabled": false
    }
  },
  "enums": {},
  "schemas": {},
  "sequences": {},
  "roles": {},
  "policies": {},
  "views": {},
  "_meta": {
    "columns": {},
    "schemas": {},
    "tables": {}
  }
}